{"head":{"description":"from the Noun Project Created by Juan Carlos Altamirano Created by iconspherefrom the Noun Project Created by Three Six Fivefrom the Noun…"},"body":"<p><text x=\"0\" y=\"44\" fill=\"#000000\" font-size=\"5px\" font-weight=\"bold\" font-family=\"'Helvetica Neue', Helvetica, Arial-Unicode, Arial, Sans-serif\">from the Noun Project</text></p>\n<p><text x=\"0\" y=\"39\" fill=\"#000000\" font-size=\"5px\" font-weight=\"bold\" font-family=\"'Helvetica Neue', Helvetica, Arial-Unicode, Arial, Sans-serif\">Created by Juan Carlos Altamirano</text></p>\n<p><text x=\"0\" y=\"115\" fill=\"#000000\" font-size=\"5px\" font-weight=\"bold\" font-family=\"'Helvetica Neue', Helvetica, Arial-Unicode, Arial, Sans-serif\">Created by iconsphere</text><text x=\"0\" y=\"120\" fill=\"#000000\" font-size=\"5px\" font-weight=\"bold\" font-family=\"'Helvetica Neue', Helvetica, Arial-Unicode, Arial, Sans-serif\">from the Noun Project</text></p>\n<p><text x=\"0\" y=\"115\" fill=\"#000000\" font-size=\"5px\" font-weight=\"bold\" font-family=\"'Helvetica Neue', Helvetica, Arial-Unicode, Arial, Sans-serif\">Created by Three Six Five</text><text x=\"0\" y=\"120\" fill=\"#000000\" font-size=\"5px\" font-weight=\"bold\" font-family=\"'Helvetica Neue', Helvetica, Arial-Unicode, Arial, Sans-serif\">from the Noun Project</text></p>\n<p><text x=\"0\" y=\"115\" fill=\"#000000\" font-size=\"5px\" font-weight=\"bold\" font-family=\"'Helvetica Neue', Helvetica, Arial-Unicode, Arial, Sans-serif\">Created by Tomasz Pasternak</text><text x=\"0\" y=\"120\" fill=\"#000000\" font-size=\"5px\" font-weight=\"bold\" font-family=\"'Helvetica Neue', Helvetica, Arial-Unicode, Arial, Sans-serif\">from the Noun Project</text></p>\n","__filename":"icon-credits.md","__url":"/icon-credits/","__resourceUrl":"/icon-credits/index.html","__dataUrl":"/icon-credits/index.html.5c20027c625f78e343a19e081802c6fb.json"}